MANIFEST.in
README.rst
requirements.txt
setup.py
django_methodview.egg-info/PKG-INFO
django_methodview.egg-info/SOURCES.txt
django_methodview.egg-info/dependency_links.txt
django_methodview.egg-info/requires.txt
django_methodview.egg-info/top_level.txt
methodview/__init__.py
methodview/accept_header.py
methodview/media_range.py
methodview/view.py
tests/unit/__init__.py
tests/unit/test_mediarange.py
tests/unit/test_view.py