Metadata-Version: 1.0
Name: django-methodview
Version: 0.3
Summary: Class based HTTP method view
Home-page: http://github.com/jkeyes/django-methodview
Author: John Keyes
Author-email: john@keyes.ie
License: MIT License
Keywords: django python http
Platform: UNKNOWN
